crd/__init__.py
crd/cli.py
crd/config.py
crd/main.py
crd/storage/__init__.py
crd/storage/abs.py
crd/storage/azure.py
crd/storage/utils.py
crd/storage/virtual.py
crd-0.0.4.data/scripts/cli.py
crd-0.0.4.data/scripts/main.py
tests/__init__.py
tests/config_test.py
tests/persistent_storage_test.py
tests/storage_test.py
tests/utils.py
crd-0.0.4.dist-info/LICENSE.md
crd-0.0.4.dist-info/METADATA
crd-0.0.4.dist-info/WHEEL
crd-0.0.4.dist-info/entry_points.txt
crd-0.0.4.dist-info/top_level.txt
crd-0.0.4.dist-info/RECORD
